jhub_remote_auth_mount/__init__.py
jhub_remote_auth_mount/_jhub_remote_auth_mount.py
jhub_remote_auth_mount-0.0.6.dist-info/METADATA
jhub_remote_auth_mount-0.0.6.dist-info/RECORD
jhub_remote_auth_mount-0.0.6.dist-info/WHEEL
jhub_remote_auth_mount-0.0.6.dist-info/top_level.txt
