Metadata-Version: 2.1
Name: jhub-remote-auth-mount
Version: 0.0.6
Summary: UNKNOWN
Home-page: https://github.com/rasmunk/jhub_remote_auth_mount
Author: Rasmus Munk
Author-email: munk1@live.dk
License: GPLv3
Keywords: Interactive,Interpreter,Shell,Web
Platform: Linux
Platform: Mac OS X
Classifier: Intended Audience :: Developers
Classifier: Intended Audience :: System Administrators
Classifier: Intended Audience :: Science/Research
Classifier: License :: OSI Approved :: GNU General Public License v3 (GPLv3)
Classifier: Programming Language :: Python
Classifier: Programming Language :: Python :: 3
Requires-Dist: jupyterhub (>=0.9.0)
Requires-Dist: docutils (>=0.13.1)
